evoml_utils/__init__.py
evoml_utils/py.typed
evoml_utils/binning/__init__.py
evoml_utils/binning/binning.py
evoml_utils/binning/dynamic_integer_array_binning.py
evoml_utils/binning/kmeans_integer_array_binning.py
evoml_utils/convertors/__init__.py
evoml_utils/convertors/map.py
evoml_utils/convertors/detected_types/__init__.py
evoml_utils/convertors/detected_types/address.py
evoml_utils/convertors/detected_types/bankcode_or_barcode.py
evoml_utils/convertors/detected_types/currency.py
evoml_utils/convertors/detected_types/datetime.py
evoml_utils/convertors/detected_types/email.py
evoml_utils/convertors/detected_types/float.py
evoml_utils/convertors/detected_types/fraction.py
evoml_utils/convertors/detected_types/geolocation.py
evoml_utils/convertors/detected_types/identity.py
evoml_utils/convertors/detected_types/int.py
evoml_utils/convertors/detected_types/ip.py
evoml_utils/convertors/detected_types/list.py
evoml_utils/convertors/detected_types/map.py
evoml_utils/convertors/detected_types/percentage.py
evoml_utils/convertors/detected_types/phone.py
evoml_utils/convertors/detected_types/protein.py
evoml_utils/convertors/detected_types/unit.py
evoml_utils/convertors/detected_types/url.py
evoml_utils/convertors/special_categorical/__init__.py
evoml_utils/convertors/special_categorical/convertor.py
evoml_utils/convertors/special_categorical/patterns.py
evoml_utils/convertors/utils/__init__.py
evoml_utils/convertors/utils/common_patterns.py
evoml_utils/convertors/utils/special_nan_to_nan.py
evoml_utils/convertors/utils/validated_column_to_column.py
evoml_utils/data/__init__.py
evoml_utils/data/data_processing.py
evoml_utils/data/explainability_scoring.py
evoml_utils/data/knowledge_bases/consistency.txt
evoml_utils/data/knowledge_bases/stability.txt
evoml_utils/logger/__init__.py
evoml_utils/logger/ttm.py
evoml_utils/metrics/__init__.py
evoml_utils/metrics/evaluation.py
evoml_utils/metrics/metrics.py
evoml_utils/metrics/specifications.py
turintech_evoml_utils-2.0.4.dist-info/LICENSE
turintech_evoml_utils-2.0.4.dist-info/METADATA
turintech_evoml_utils-2.0.4.dist-info/WHEEL
turintech_evoml_utils-2.0.4.dist-info/top_level.txt
turintech_evoml_utils-2.0.4.dist-info/RECORD
